pretty_logger/__init__.py
pretty_logger/constants.py
pretty_logger/decorators.py
pretty_logger/file_logger.py
kayer_pretty_logger-1.2.1.dist-info/METADATA
kayer_pretty_logger-1.2.1.dist-info/WHEEL
kayer_pretty_logger-1.2.1.dist-info/top_level.txt
kayer_pretty_logger-1.2.1.dist-info/RECORD
