Metadata-Version: 2.1
Name: kayer-pretty-logger
Version: 1.2.1
Summary: A pretty and colorful logger to emulate nest.js's logger and overwrite the python print function.
Home-page: https://github.com/PilotKayer/pretty_logger
Author: Kayer
Author-email: devkayer@gmail.com
Project-URL: Docs, https://github.com/PilotKayer/pretty_logger/blob/main/README.md
Classifier: Programming Language :: Python :: 3
Classifier: License :: OSI Approved :: MIT License
Classifier: Operating System :: OS Independent
Requires-Python: >=3.10
